riccati/__init__.py
riccati/_version.py
riccati/chebutils.py
riccati/evolve.py
riccati/solversetup.py
riccati/step.py
riccati/stepsize.py
riccati/tests/__init__.py
riccati/tests/test_riccati.py
riccati-2.0.0.dist-info/LICENSE
riccati-2.0.0.dist-info/METADATA
riccati-2.0.0.dist-info/WHEEL
riccati-2.0.0.dist-info/top_level.txt
riccati-2.0.0.dist-info/RECORD
