Metadata-Version: 2.1
Name: riccati
Version: 2.0.0
Summary: adaptive Riccati defect correction solver
Home-page: 
Author: Fruzsina J Agocs and Alex H Barnett
Author-email: 
License: Apache 2.0
License-File: LICENSE
Requires-Dist: numpy
Provides-Extra: all
Requires-Dist: sphinx ; extra == 'all'
Requires-Dist: sphinx-book-theme ; extra == 'all'
Requires-Dist: numpydoc ; extra == 'all'
Requires-Dist: numpy ; extra == 'all'
Requires-Dist: scipy ; extra == 'all'
Requires-Dist: mpmath ; extra == 'all'
Requires-Dist: pytest ; extra == 'all'
Requires-Dist: pandas ; extra == 'all'
Requires-Dist: num2tex ; extra == 'all'
Requires-Dist: matplotlib ; extra == 'all'
Requires-Dist: pyoscode ; extra == 'all'
Provides-Extra: docs
Requires-Dist: sphinx ; extra == 'docs'
Requires-Dist: sphinx-book-theme ; extra == 'docs'
Requires-Dist: numpydoc ; extra == 'docs'
Provides-Extra: plots
Requires-Dist: pandas ; extra == 'plots'
Requires-Dist: num2tex ; extra == 'plots'
Requires-Dist: matplotlib ; extra == 'plots'
Requires-Dist: pyoscode ; extra == 'plots'
Provides-Extra: tests
Requires-Dist: numpy ; extra == 'tests'
Requires-Dist: scipy ; extra == 'tests'
Requires-Dist: mpmath ; extra == 'tests'
Requires-Dist: pytest ; extra == 'tests'
